{"cameraMode":{"drawMode":0,"name":"Shaded","section":"Shading Mode"},"sceneLighting":true,"audioPlay":false,"sceneViewState":{"showFog":true,"showMaterialUpdate":false,"showSkybox":true,"showFlares":true,"showImageEffects":true,"showParticleSystems":true},"in2DMode":false,"pivot":{"x":48.31808090209961,"y":9.505465507507325,"z":3.300278902053833},"rotation":{"x":-0.42300423979759219,"y":0.5564008951187134,"z":-0.3945438265800476,"w":-0.5965336561203003},"size":16.963659286499025,"orthographic":false}